appodus_utils/__init__.py
appodus_utils/alembic/README
appodus_utils/alembic/env.py
appodus_utils/alembic/script.py.mako
appodus_utils/alembic/versions/fdd959a2cfda_auto_generated.py
appodus_utils/common/__init__.py
appodus_utils/common/appodus_test_utils.py
appodus_utils/common/auth_utils.py
appodus_utils/common/client_utils.py
appodus_utils/common/commons.py
appodus_utils/common/context_utils.py
appodus_utils/common/utils_settings.py
appodus_utils/config/__init__.py
appodus_utils/config/bootstrap.py
appodus_utils/config/client_manager.py
appodus_utils/config/logger.py
appodus_utils/config/settings.py
appodus_utils/db/__init__.py
appodus_utils/db/db_utils.py
appodus_utils/db/models.py
appodus_utils/db/redis_utils.py
appodus_utils/db/repo.py
appodus_utils/db/session.py
appodus_utils/db/types/loci.py
appodus_utils/db/types/money.py
appodus_utils/decorators/decorate_all_methods.py
appodus_utils/decorators/method_trace_logger.py
appodus_utils/decorators/require_roles.py
appodus_utils/decorators/transactional.py
appodus_utils/domain/__init__.py
appodus_utils/domain/bot/__init__.py
appodus_utils/domain/bot/models.py
appodus_utils/domain/bot/chat/__init__.py
appodus_utils/domain/bot/chat/models.py
appodus_utils/domain/bot/chat/history/__init__.py
appodus_utils/domain/bot/chat/history/models.py
appodus_utils/domain/client/__init__.py
appodus_utils/domain/client/controller.py
appodus_utils/domain/client/models.py
appodus_utils/domain/client/repo.py
appodus_utils/domain/client/service.py
appodus_utils/domain/client/validator.py
appodus_utils/domain/contract/__init__.py
appodus_utils/domain/contract/models.py
appodus_utils/domain/document/__init__.py
appodus_utils/domain/document/models.py
appodus_utils/domain/key_value/__init__.py
appodus_utils/domain/key_value/models.py
appodus_utils/domain/key_value/repo.py
appodus_utils/domain/key_value/service.py
appodus_utils/domain/message/__init__.py
appodus_utils/domain/message/message_sender.py
appodus_utils-0.149.0.dist-info/licenses/LICENSE
appodus_utils-0.149.0.dist-info/METADATA
appodus_utils-0.149.0.dist-info/WHEEL
appodus_utils-0.149.0.dist-info/top_level.txt
appodus_utils-0.149.0.dist-info/RECORD
