Metadata-Version: 2.4
Name: appodus-utils
Version: 0.149.0
Summary: A collection of appodus commonly used utility functions
Author-email: kingsley ezenwere <kingsley.ezenwere@gmail.com>
License: MIT License
Requires-Python: >=3.8
License-File: LICENSE
Requires-Dist: python-jose<3.5.0,>=3.4.0
Requires-Dist: inflection<0.6.0,>=0.5.1
Requires-Dist: Jinja2<3.2.0,>=3.1.6
Requires-Dist: passlib[bcrypt]<1.8.0,>=1.7.4
Requires-Dist: kink<0.9.0,>=0.8.1
Requires-Dist: sqlalchemy[asyncio]<2.1.0,>=2.0.40
Requires-Dist: pydantic<2.12.0,>=2.11.5
Requires-Dist: fastapi<0.116.0,>=0.115.12
Requires-Dist: redis<5.3.0,>=5.2.1
Requires-Dist: libre-fastapi-jwt<0.23.0,>=0.22.8
Dynamic: license-file
